LICENSE
README.md
pdftxt/__init__.py
pdftxt/api.py
pdftxt/cli.py
pdftxt/grid.py
pdftxt/html.py
pdftxt/miner.py
pdftxt/region.py
pdftxt/util.py
pdftxt-0.3.2.dist-info/entry_points.txt
pdftxt-0.3.2.dist-info/LICENSE
pdftxt-0.3.2.dist-info/WHEEL
pdftxt-0.3.2.dist-info/METADATA
pdftxt-0.3.2.dist-info/RECORD
