Metadata-Version: 2.1
Name: pdftxt
Version: 0.3.2
Summary: PDF text extractor.
Home-page: https://bitbucket.org/mgemmill/pdftxt
License: BSD-3-Clause
Author: Mark Gemmill
Author-email: bitbucket@markgemmill.com
Requires-Python: >=3.6,<4.0
Classifier: Development Status :: 4 - Beta
Classifier: Intended Audience :: Developers
Classifier: License :: OSI Approved :: BSD License
Classifier: Programming Language :: Python :: 3
Classifier: Programming Language :: Python :: 3.6
Classifier: Programming Language :: Python :: 3.7
Requires-Dist: docopt (>=0.6.2,<0.7.0)
Requires-Dist: pdfminer.six (>=20181108.0,<20181109.0)
